{
  "NOTE": "This is a hand-crafted example of what multiple REST Responses would aggregate.",
  "Flows": {
    "3175306b-0155-e911-a2c0-c4346bcb1554": {
      "Related": [{
        "Id": "3175306b-0155-e911-a2c0-c4346bcb1554",
        "Name": "Vector model comparison",
        "Owner": "pselvaraj",
        "Relationship": "Subject",
        "ObjectType": "WorkItem",
        "DateCreated": "2019-07-02T04:40:29.8630000Z",
        "LastModified": "2019-07-02T04:43:34.8300000Z",
        "State": "Waiting",
        "Worker": {
          "Name": "DockerWorker",
          "Version": "1.0.0.0_RELEASE"
        }
      }, {
        "Id": "7f8a723d-5f54-e911-a2c0-c4346bcb1554",
        "Relationship": "DependsOn",
        "ObjectType": "Experiment",
        "Name": "Ivermectin_nochildbearingage_new_vector_model",
        "Owner": "pselvaraj",
        "DateCreated": "2019-04-01T09:19:25.1030000Z",
        "LastModified": "2019-04-01T09:19:25.1030000Z",
        "SimulationCount": 4400,
        "SimulationStateCount": {
          "Commissioned": 400,
          "Running": 1000,
          "Succeeded": 3000
        }
      }, {
        "Id": "aeb59903-d254-e911-a2c0-c4346bcb1554",
        "Relationship": "DependsOn",
        "ObjectType": "Experiment",
        "Name": "Ivermectin_nochildbearingage_old_vector_model",
        "Owner": "pselvaraj",
        "DateCreated": "2019-04-01T23:01:05.4730000Z",
        "LastModified": "2019-04-01T23:01:05.4730000Z",
        "SimulationCount": 4400,
        "SimulationStateCount": {
          "Running": 400,
          "Succeeded": 4000
        }
      }]
    }
  }
}